webpall/__init__.py
webpall/converter.py
webpall-0.1.2.dist-info/METADATA
webpall-0.1.2.dist-info/WHEEL
webpall-0.1.2.dist-info/entry_points.txt
webpall-0.1.2.dist-info/top_level.txt
webpall-0.1.2.dist-info/RECORD
