Metadata-Version: 2.1
Name: webpall
Version: 0.1.2
Summary: Convert JPG and PNG images in a folder to WebP format with selective options.
Author: Rishikesh Sreehari
Author-email: contact@rishikeshs.com
Classifier: Programming Language :: Python :: 3
Classifier: License :: OSI Approved :: MIT License
Classifier: Operating System :: OS Independent
Requires-Python: >=3.6
Requires-Dist: Pillow
